LassaLib/__init__.py
lassalib-3.1.2.dist-info/METADATA
lassalib-3.1.2.dist-info/WHEEL
lassalib-3.1.2.dist-info/licenses/LICENSE
lassalib-3.1.2.dist-info/RECORD
