Metadata-Version: 2.1
Name: LassaLib
Version: 3.1.2
Summary: Convenient function set
Project-URL: Homepage, https://github.com/LassaInora/LassaLib
Project-URL: Bug Tracker, https://github.com/LassaInora/LassaLib/issues
Author-email: Axelle Viandier <lassainora@lassainora.fr>
License-File: LICENSE
Classifier: License :: OSI Approved :: GNU General Public License v3 (GPLv3)
Classifier: Operating System :: OS Independent
Classifier: Programming Language :: Python :: 3
Requires-Python: >=3.6
